test_esther_young/__init__.py
test_esther_young/ice_breaking.py
test_esther_young/api/call.py
test_esther_Young-0.1.2.dist-info/METADATA
test_esther_Young-0.1.2.dist-info/WHEEL
test_esther_Young-0.1.2.dist-info/entry_points.txt
test_esther_Young-0.1.2.dist-info/top_level.txt
test_esther_Young-0.1.2.dist-info/RECORD
