Metadata-Version: 2.1
Name: test_esther_Young
Version: 0.1.2
Summary: Default template for PDM package
Author-email: Nicou11 <lyoungin1204@gmail.com>
License: MIT
Requires-Python: >=3.9
Requires-Dist: pyfiglet >=1.0.2
